statify/__init__.py
statify/config.py
statify/database_client.py
statify/spotify_client.py
statify/statify.py
statify/webserver/__init__.py
statify/webserver/search.py
statify/webserver/webserver.py
statify/webserver/static/autocomplete.js
statify/webserver/static/common.css
statify/webserver/static/front.css
statify/webserver/static/song.css
statify/webserver/static/song.js
statify/webserver/templates/autocomplete_template.html
statify/webserver/templates/index.html
statify/webserver/templates/song.html
statify-1.3.0.dist-info/METADATA
statify-1.3.0.dist-info/WHEEL
statify-1.3.0.dist-info/entry_points.txt
statify-1.3.0.dist-info/top_level.txt
statify-1.3.0.dist-info/RECORD
